elasticsearchpy/__init__.py
elasticsearchpy/bases.py
elasticsearchpy/cluster.py
elasticsearchpy/documents.py
elasticsearchpy/exceptions.py
elasticsearchpy/host.py
elasticsearchpy/indices.py
elasticsearchpy/node.py
tests/unit/__init__.py
tests/unit/test_cluster.py
tests/unit/test_host.py
tests/unit/test_indice.py
tests/unit/test_indices.py
tests/unit/unit_test_base.py
elasticsearch_python_client-0.0.1.dist-info/LICENSE
elasticsearch_python_client-0.0.1.dist-info/METADATA
elasticsearch_python_client-0.0.1.dist-info/WHEEL
elasticsearch_python_client-0.0.1.dist-info/top_level.txt
elasticsearch_python_client-0.0.1.dist-info/RECORD
