Metadata-Version: 2.1
Name: elasticsearch-python-client
Version: 0.0.1
Summary: An Alternative ElasticSearch Python Library
Home-page: https://github.com/koebane82/elasticsearchpy
Author: koebane82
Author-email: jeff@koebane.net
License: UNKNOWN
Platform: UNKNOWN
Classifier: License :: OSI Approved :: GNU General Public License v3 (GPLv3)
Classifier: Operating System :: OS Independent
Classifier: Programming Language :: Python :: 3
Classifier: Programming Language :: Python :: 3.3
Classifier: Programming Language :: Python :: 3.4
Classifier: Programming Language :: Python :: 3.5
Classifier: Programming Language :: Python :: 3.6
Classifier: Programming Language :: Python :: 3.7
